[
  { "name": "刘亦菲", "emoji": "🌸", "works": "仙剑奇侠传·赵灵儿, 神雕侠侣·小龙女", "color": "#c9a84c", "intro": "神仙姐姐，华语最具国际知名度的女演员之一。", "bio": "生于武汉，成长于美国。2002年因出演《金粉世家》出道，2004年因《仙剑奇侠传》赵灵儿一角色红遍亚洲。2006年出演《神雕侠侣》小龙女，被誉为\"最接近原著的小龙女\"。2008年出演《功夫之王》进军好莱坞。代表作还包括《花木兰》《三生三世十里桃花》《梦华录》。", "quote": "我希望自己是一个演员，而不是明星。", "death": "（活跃中）", "influence": "华语女演员国际知名度代表" },
  { "name": "刘诗诗", "emoji": "🌙", "works": "仙剑三·龙葵, 步步惊心·若曦", "color": "#6b8db5", "intro": "气质女神，古典美人的代表。", "bio": "生于北京，毕业于北京舞蹈学院。2009年因《仙剑奇侠传三》龙葵角色走红。2011年主演《步步惊心》饰演马尔泰·若曦，成为经典。她以优雅气质和自然演技著称，代表作还包括《轩辕剑》《女医·明妃传》《亲爱的自己》。", "quote": "优雅，是永远不褪色的美丽。", "death": "（活跃中）", "influence": "古典美人的代表" },
  { "name": "赵丽颖", "emoji": "🌺", "works": "花千骨·花千骨, 楚乔传·楚乔", "color": "#d43c2a", "intro": "从草根到顶流，最励志的奋斗故事。", "bio": "生于河北廊坊，非科班出身。2011年因《新还珠格格》晴儿初露锋芒。2015年主演《花千骨》创下收视纪录，成为现象级女演员。2017年《楚乔传》播放量突破150亿。她以扎实演技和坚韧意志著称，代表作还包括《知否》《风吹半夏》。", "quote": "没有人一开始就是高手，都是慢慢练出来的。", "death": "（活跃中）", "influence": "最励志的非科班女演员" },
  { "name": "迪丽热巴", "emoji": "🔥", "works": "三生三世·凤九, 烈火如歌·烈如歌", "color": "#d43c2a", "intro": "异域风情的美女，30+岁依然演技在线。", "bio": "生于新疆乌鲁木齐。2013年因《古剑奇谭》襄铃出道。2017年《三生三世十里桃花》凤九一角大红，成为\"90后\"最具代表性女演员。近年转型实力派，代表作还包括《长歌行》《与君歌》《恰似故人归》。", "quote": "美，是一种态度。", "death": "（活跃中）", "influence": "90后最具代表性女演员" },
  { "name": "杨颖（Angelababy）", "emoji": "💎", "works": "孤芳·白娉婷, 孤芳不自赏", "color": "#c9a84c", "intro": "时尚icon，从模特到演员的多栖发展。", "bio": "生于上海。2003年因广告模特出道，2011年因《奔跑吧兄弟》人气飙升。影视代表作包括《孤芳不自赏》《寻龙诀》《孤芳不自赏》。她以时尚感和商业价值著称，是品牌商最青睐的女演员之一。", "quote": "时尚是一种态度，不是年龄。", "death": "（活跃中）", "influence": "时尚圈最具影响力的女演员" },
  { "name": "古力娜扎", "emoji": "🌟", "works": "轩辕剑·小雪, 风起陇西·柳莹", "color": "#8a6d8a", "intro": "新疆最美的花朵，影视歌多栖发展。", "bio": "生于新疆乌鲁木齐。2011年因《轩辕剑之天之痕》小雪出道，被誉为\"最美古力娜扎\"。她以高挑身材和异域风情的美貌著称，代表作还包括《爱人同学录》《武神赵子龙》《风暴舞》。", "quote": "美丽是一种责任。", "death": "（活跃中）", "influence": "新疆最知名的女演员" },
  { "name": "陈乔恩", "emoji": "🌹", "works": "笑傲江湖·东方不败, 何以笙箫默·赵默笙", "color": "#a03030", "intro": "台剧女王，从偶像剧到正剧的完美跨越。", "bio": "生于中国台湾。2004年因《王子变青蛙》走红，被誉为\"台剧女王\"。2014年《何以笙箫默》赵默笙一角大陆爆红。她以自然演技和优雅气质著称，代表作还包括《胜女的时代》《独孤天下》。", "quote": "爱情不是必需品，但有了是惊喜。", "death": "（活跃中）", "influence": "台剧女王，跨海峡最受欢迎女演员" },
  { "name": "唐嫣", "emoji": "🌸", "works": "仙剑三·紫萱, 锦绣未央·李未央", "color": "#c9a84c", "intro": "甜妹天花板，从偶像剧到实力派的蜕变。", "bio": "生于上海。2009年因《仙剑三》紫萱走红。2016年《锦绣未央》李未央展现演技突破。她以甜美笑容和亲和力著称，代表作还包括《何以笙箫默》《何以笙箫默》《归路》。", "quote": "甜，不是标签，是态度。", "death": "（活跃中）", "influence": "甜美系女演员代表" },
  { "name": "白鹿", "emoji": "🦌", "works": "周生如故·漼时宜, 长月烬明·黎苏苏", "color": "#d43c2a", "intro": "从网红到顶流的逆袭故事。", "bio": "生于江苏常州。2016年因《朝歌》出道。2021年《周生如故》漼时宜一角爆红，\"哭戏\"成为全网话题。她以真诚个性和自然演技著称，代表作还包括《长月烬明》《半是蜜糖半是伤》《宁安如梦》。", "quote": "真诚是最好的演技。", "death": "（活跃中）", "influence": "新生代最具人气女演员" },
  { "name": "杨幂", "emoji": "👑", "works": "宫锁心玉·洛晴川, 三生三世·白浅", "color": "#c9a84c", "intro": "85花顶流，从流量到实力的传奇。", "bio": "生于北京。2011年因《宫锁心玉》洛晴川爆红，成为\"85花\"最顶级流量。2017年《三生三世十里桃花》白浅展现演技实力。她以商业头脑和公众影响力著称，代表作还包括《小时代》《谈判官》《斛珠夫人》。", "quote": "我不是天才，我只是够努力。", "death": "（活跃中）", "influence": "85花顶流，最具商业价值女演员" },
  { "name": "赵露思", "emoji": "🌸", "works": "传闻中的陈芊芊, 星汉灿烂·程少商", "color": "#d43c2a", "intro": "新生代甜妹女王，短剧时代的超级新星。", "bio": "生于四川成都。2019年因《传闻中的陈芊芊》走红。2022年《星汉灿烂》程少商展现演技突破。她以灵动笑容和自然演技著称，代表作还包括《长歌行》《且试天下》《星汉灿烂》。", "quote": "做最真实的自己。", "death": "（活跃中）", "influence": "新生代甜妹女王" },
  { "name": "谭松韵", "emoji": "🌺", "works": "甄嬛传·淳贵人, 以家人之名·李尖尖", "color": "#d43c2a", "intro": "童颜天后，从\"淳贵人\"到\"李尖尖\"的蜕变。", "bio": "生于四川遂宁。2011年因《甄嬛传》淳贵人被观众熟知。2020年《以家人之名》李尖尖展现自然演技，成为国民\"妹妹\"。她以天然童颜和灵动演技著称，代表作还包括《锦衣之下》《民初奇人传》《归路》。", "quote": "童颜不是标签，是天然馈赠。", "death": "（活跃中）", "influence": "童颜天后的代表" }
]
